[{"model": "catalog.book", "pk": 1, "fields": {"title": "The Hobbit", "author": 1, "summary": "The history of the Middle Earth", "isbn": "054792822X", "language": 40, "genre": [2, 5, 10]}}, {"model": "catalog.book", "pk": 2, "fields": {"title": "Harry Potter and the Philosopher's Stone", "author": 2, "summary": "The magic world of Harry Potter", "isbn": "1526602385", "language": 40, "genre": [1, 10]}}, {"model": "catalog.book", "pk": 3, "fields": {"title": "The Little Prince", "author": 3, "summary": "", "isbn": "0156012197", "language": 47, "genre": [1]}}, {"model": "catalog.book", "pk": 4, "fields": {"title": "Dream of the Red Chamber", "author": 4, "summary": "", "isbn": "1981791493", "language": 30, "genre": [11]}}, {"model": "catalog.book", "pk": 5, "fields": {"title": "And Then There Were None", "author": 5, "summary": "", "isbn": "0062875914", "language": 40, "genre": [2, 11]}}]